{
  "holdings": [
    {
      "code": "005930",
      "name": "삼성전자",
      "quantity": 2,
      "avgPrice": 203500,
      "currentPrice": 203500,
      "profit": 0,
      "profitRate": 0,
      "buyDate": "2026-04-09T01:52:13.521Z",
      "partialSells": [],
      "highestPrice": 203500
    },
    {
      "code": "036570",
      "name": "엔씨소프트",
      "quantity": 2,
      "avgPrice": 233500,
      "buyDate": "2026-04-09T06:19:34.410Z",
      "orderNo": "0000032720"
    }
  ],
  "summary": {
    "totalDeposit": 9696361,
    "totalEvaluation": 10643295,
    "totalProfit": 0
  },
  "lastUpdated": "2026-04-09T06:19:34.410Z"
}