{
  "holdings": [
    {
      "code": "005930",
      "name": "삼성전자",
      "quantity": 2,
      "avgPrice": 217125,
      "currentPrice": 292500,
      "profit": 150750,
      "profitRate": 34.72,
      "buyDate": null,
      "partialSells": [],
      "highestPrice": 299500
    },
    {
      "code": "036570",
      "name": "NC",
      "quantity": 1,
      "avgPrice": 266000,
      "currentPrice": 276000,
      "profit": 10000,
      "profitRate": 3.76,
      "buyDate": null,
      "partialSells": [],
      "highestPrice": 282500
    },
    {
      "code": "055550",
      "name": "신한지주",
      "quantity": 5,
      "avgPrice": 99880,
      "currentPrice": 98200,
      "profit": -8400,
      "profitRate": -1.68,
      "buyDate": null,
      "partialSells": [],
      "highestPrice": 100300
    },
    {
      "code": "086790",
      "name": "하나금융지주",
      "quantity": 4,
      "avgPrice": 122000,
      "currentPrice": 122100,
      "profit": 400,
      "profitRate": 0.08,
      "buyDate": null,
      "partialSells": [],
      "highestPrice": 129000
    },
    {
      "code": "105560",
      "name": "KB금융",
      "quantity": 3,
      "avgPrice": 161500,
      "currentPrice": 160000,
      "profit": -4500,
      "profitRate": -0.93,
      "buyDate": null,
      "partialSells": [],
      "highestPrice": 162400
    }
  ],
  "summary": {
    "totalDeposit": 8584458,
    "totalEvaluation": 10904858,
    "totalProfit": 148250
  },
  "lastUpdated": "2026-05-22T06:45:21.890Z"
}